<?xml version="1.0" encoding="utf-8"?>
<annotation>
	<image>2007_007698</image>
	<voc_id>1</voc_id>
	<category>aeroplane</category>
	<subcategory>Propeller</subcategory>
	<visible_bounds height="68.00" width="142.00" xmin="185.00" ymin="142.00"/>
	<keypoints>
		<keypoint name="Top_Rudder" visible="1" x="203.98" y="206.40" z="0.00"/>
		<keypoint name="Bot_Rudder" visible="1" x="208.58" y="189.81" z="0.00"/>
		<keypoint name="L_Stabilizer" visible="1" x="190.04" y="176.50" z="0.00"/>
		<keypoint name="R_Stabilizer" visible="1" x="235.16" y="200.98" z="0.00"/>
		<keypoint name="L_WingTip" visible="1" x="195.78" y="144.79" z="0.00"/>
		<keypoint name="R_WingTip" visible="1" x="322.78" y="205.74" z="0.00"/>
		<keypoint name="NoseTip" visible="1" x="281.60" y="178.55" z="0.00"/>
		<keypoint name="Nose_Top" visible="1" x="265.30" y="184.17" z="0.00"/>
		<keypoint name="Nose_Bottom" visible="1" x="278.73" y="174.28" z="0.00"/>
		<keypoint name="Left_Wing_Base" visible="1" x="247.58" y="169.49" z="0.00"/>
		<keypoint name="Right_Wing_Base" visible="1" x="277.82" y="184.55" z="0.00"/>
		<keypoint name="Bot_Rudder_Front" visible="1" x="220.78" y="187.78" z="0.00"/>
	</keypoints>
</annotation>
