<?xml version="1.0" encoding="utf-8"?>
<annotation>
	<image>2008_006337</image>
	<voc_id>3</voc_id>
	<category>pottedplant</category>
	<visible_bounds height="81.00" width="47.00" xmin="100.00" ymin="264.00"/>
	<keypoints>
		<keypoint name="Top_Left" visible="1" x="103.78" y="294.15" z="0.00"/>
		<keypoint name="Top_Right" visible="1" x="144.80" y="292.06" z="0.00"/>
		<keypoint name="Top_Front_Middle" visible="1" x="124.05" y="301.71" z="0.00"/>
		<keypoint name="Top_Back_Middle" visible="1" x="128.56" y="283.80" z="0.00"/>
		<keypoint name="Bottom_Left" visible="1" x="113.44" y="325.32" z="0.00"/>
		<keypoint name="Bottom_Right" visible="1" x="138.52" y="323.75" z="0.00"/>
	</keypoints>
	<polylinesegments>
		<segment name="foreground" x="142.72 121.36 113.44 110.80 109.60 111.04 110.32 103.60 102.64 104.32 102.64 104.08 114.88 125.92 134.32 136.96 136.72 135.28 143.92 146.08 145.36 142.00 142.96 145.84 " y="337.96 339.88 339.40 337.96 334.35 324.96 318.22 299.20 293.19 290.06 282.12 277.06 269.36 265.99 269.12 272.49 278.02 282.60 285.97 291.74 300.17 317.74 326.88 336.99 "/>
	</polylinesegments>
</annotation>
