<?xml version="1.0" encoding="utf-8"?>
<annotation>
	<image>2010_004609</image>
	<voc_id>2</voc_id>
	<category>bottle</category>
	<visible_bounds height="52.00" width="42.00" xmin="220.00" ymin="165.00"/>
	<keypoints>
		<keypoint name="L_Top" visible="1" x="254.69" y="167.77" z="0.00"/>
		<keypoint name="R_Top" visible="1" x="258.66" y="170.22" z="0.00"/>
		<keypoint name="L_Neck" visible="1" x="245.98" y="175.24" z="0.00"/>
		<keypoint name="R_Neck" visible="1" x="253.52" y="181.19" z="0.00"/>
		<keypoint name="L_Shoulder" visible="1" x="241.00" y="176.40" z="0.00"/>
		<keypoint name="R_Shoulder" visible="1" x="254.33" y="186.52" z="0.00"/>
		<keypoint name="L_Base" visible="1" x="220.86" y="206.22" z="0.00"/>
		<keypoint name="R_Base" visible="1" x="233.22" y="215.41" z="0.00"/>
	</keypoints>
	<polylinesegments>
		<segment name="foreground" x="220.47 232.29 229.49 242.40 247.07 249.40 256.09 259.82 252.98 256.40 250.80 251.11 234.00 227.93 220.16 " y="198.73 186.36 183.58 175.09 175.70 172.15 167.05 171.99 180.03 184.82 195.64 199.19 215.57 213.10 206.14 "/>
	</polylinesegments>
</annotation>
