<?xml version="1.0" encoding="utf-8"?>
<annotation>
	<image>2008_003997</image>
	<voc_id>1</voc_id>
	<category>bird</category>
	<subcategory>Flying</subcategory>
	<visible_bounds height="235.00" width="309.00" xmin="4.00" ymin="26.00"/>
	<keypoints>
		<keypoint name="Left_Eye" visible="1" x="104.23" y="178.76" z="0.00"/>
		<keypoint name="Beak_Base" visible="1" x="92.09" y="187.21" z="0.00"/>
		<keypoint name="Beak_Tip" visible="1" x="80.66" y="196.14" z="0.00"/>
		<keypoint name="Lower_Neck_Base" visible="1" x="124.94" y="199.00" z="0.00"/>
		<keypoint name="Upper_Neck_Base" visible="1" x="120.29" y="174.36" z="0.00"/>
		<keypoint name="Leg_Center" visible="1" x="230.87" y="191.62" z="0.00"/>
		<keypoint name="Left_Wing_Base" visible="1" x="137.79" y="164.71" z="0.00"/>
		<keypoint name="Left_Wing_Tip" visible="1" x="29.96" y="38.76" z="0.00"/>
		<keypoint name="Right_Wing_Tip" visible="1" x="201.35" y="36.14" z="0.00"/>
		<keypoint name="Tail_Tip" visible="1" x="304.90" y="182.57" z="0.00"/>
	</keypoints>
	<polylinesegments>
		<segment name="foreground" x="15.67 27.81 42.10 58.52 66.38 70.66 83.52 109.94 128.51 135.65 118.51 99.23 94.23 82.09 74.23 74.23 89.23 96.37 109.22 128.51 159.21 191.35 226.34 234.91 238.48 241.34 247.77 255.62 259.91 269.19 269.90 263.48 252.05 246.34 243.48 236.34 241.34 247.05 251.34 257.05 261.34 267.05 273.48 277.05 282.05 288.47 290.61 285.62 277.76 270.62 261.34 254.19 251.34 259.91 272.05 277.05 285.62 293.47 298.47 306.33 311.32 308.47 295.61 283.47 262.76 250.62 242.77 237.77 236.34 240.63 242.77 244.20 243.48 239.91 237.05 229.91 222.06 213.49 204.20 198.49 196.35 182.78 169.21 144.93 112.80 77.80 69.95 62.09 51.38 44.24 38.53 32.10 23.53 22.81 22.10 17.10 15.67 15.67 15.67 15.67 14.25 " y="59.71 82.57 97.57 111.14 115.43 124.71 128.29 139.71 154.71 165.43 169.00 176.14 184.71 188.29 195.43 201.86 199.71 195.43 199.00 203.29 205.43 204.71 195.43 199.00 204.71 222.57 237.57 246.86 254.71 254.71 246.14 233.29 221.86 208.29 197.57 191.14 190.43 196.86 201.86 212.57 219.00 224.71 230.43 236.86 238.29 239.00 234.00 229.71 221.14 214.71 205.43 194.00 190.43 191.14 191.14 191.14 188.29 189.00 191.14 191.14 187.57 178.29 173.29 169.71 163.29 159.71 152.57 144.71 131.14 123.29 111.86 101.86 86.86 74.71 59.00 49.00 41.14 34.00 30.43 34.71 41.14 77.57 104.71 90.43 65.43 48.29 46.86 37.57 39.71 31.14 34.71 34.71 31.86 40.43 46.86 54.00 54.71 54.71 53.29 53.29 53.29 "/>
	</polylinesegments>
</annotation>
