<?xml version="1.0" encoding="utf-8"?>
<annotation>
	<image>2008_004910</image>
	<voc_id>1</voc_id>
	<category>tvmonitor</category>
	<visible_bounds height="98.00" width="113.00" xmin="237.00" ymin="158.00"/>
	<keypoints>
		<keypoint name="F_Top_Left" visible="1" x="340.95" y="168.17" z="0.00"/>
		<keypoint name="F_Top_Right" visible="1" x="244.79" y="174.09" z="0.00"/>
		<keypoint name="F_Bottom_Left" visible="1" x="341.15" y="238.35" z="0.00"/>
		<keypoint name="F_Bottom_Right" visible="1" x="247.21" y="249.32" z="0.00"/>
	</keypoints>
	<polylinesegments>
		<segment name="foreground" x="237.61 240.23 245.76 249.25 249.25 340.66 340.08 344.15 342.99 333.96 " y="170.02 247.77 250.97 250.97 253.59 243.40 241.36 240.78 165.07 162.45 "/>
	</polylinesegments>
</annotation>
