<?xml version="1.0" encoding="utf-8"?>
<annotation>
	<image>2009_004228</image>
	<category>diningtable</category>
	<visible_bounds height="140.00" width="423.00" xmin="1.00" ymin="235.00"/>
	<keypoints>
		<keypoint name="Top_Left_Back" visible="1" x="126.86" y="240.12" z="0.00"/>
		<keypoint name="Top_Right_Back" visible="1" x="375.76" y="247.54" z="0.00"/>
	</keypoints>
	<polylinesegments>
		<segment name="foreground" x="421.71 -0.62 58.04 118.65 254.54 376.74 381.62 " y="369.49 372.42 297.18 234.65 233.67 239.53 243.44 "/>
	</polylinesegments>
</annotation>
