<?xml version="1.0" encoding="utf-8"?>
<annotation>
	<image>2010_004380</image>
	<category>diningtable</category>
	<visible_bounds height="86.00" width="177.00" xmin="86.00" ymin="94.00"/>
	<keypoints>
		<keypoint name="Top_Left_Front" visible="1" x="89.01" y="166.30" z="0.00"/>
		<keypoint name="Top_Left_Back" visible="1" x="107.69" y="97.73" z="0.00"/>
		<keypoint name="Top_Right_Front" visible="1" x="260.61" y="168.76" z="0.00"/>
		<keypoint name="Top_Right_Back" visible="1" x="240.77" y="104.68" z="0.00"/>
	</keypoints>
	<polylinesegments>
		<segment name="foreground" x="259.59 242.00 105.37 86.55 88.19 " y="178.36 101.55 95.01 164.87 179.17 "/>
	</polylinesegments>
</annotation>
