<?xml version="1.0" encoding="utf-8"?>
<annotation>
	<image>2010_005901</image>
	<category>diningtable</category>
	<visible_bounds height="142.00" width="418.00" xmin="1.00" ymin="233.00"/>
	<keypoints>
		<keypoint name="Top_Left_Back" visible="1" x="66.38" y="236.40" z="0.00"/>
		<keypoint name="Top_Right_Back" visible="1" x="392.26" y="293.38" z="0.00"/>
	</keypoints>
	<polylinesegments>
		<segment name="foreground" x="0.37 67.03 380.02 425.43 402.24 46.74 10.99 -5.43 " y="325.25 377.39 375.46 326.21 288.55 219.02 213.22 226.74 "/>
	</polylinesegments>
</annotation>
