<?xml version="1.0" encoding="utf-8"?>
<annotation>
	<image>2009_001268</image>
	<voc_id>1</voc_id>
	<category>sofa</category>
	<visible_bounds height="126.00" width="255.00" xmin="1.00" ymin="182.00"/>
	<keypoints>
		<keypoint name="Back_Top_Left" visible="1" x="237.38" y="187.61" z="0.00"/>
		<keypoint name="Front_Base_Left" visible="1" x="236.64" y="297.24" z="0.00"/>
		<keypoint name="Left_Junction" visible="1" x="220.83" y="230.48" z="0.00"/>
		<keypoint name="Handle_Front_Left" visible="1" x="238.41" y="237.35" z="0.00"/>
		<keypoint name="Handle_Left_Junction" visible="1" x="242.83" y="218.51" z="0.00"/>
	</keypoints>
	<polylinesegments>
		<segment name="foreground" x="2.97 251.67 251.08 246.96 249.90 251.67 245.19 246.37 244.60 245.19 246.37 233.99 230.45 225.74 3.56 2.38 " y="180.85 183.20 201.45 226.75 233.82 251.47 251.47 299.74 300.33 304.45 305.03 306.21 302.09 299.15 296.79 296.21 "/>
	</polylinesegments>
</annotation>
