<?xml version="1.0" encoding="utf-8"?>
<annotation>
	<image>2011_000499</image>
	<voc_id>4</voc_id>
	<category>sofa</category>
	<visible_bounds height="168.00" width="214.00" xmin="286.00" ymin="166.00"/>
	<keypoints>
		<keypoint name="Back_Top_Right" visible="1" x="351.46" y="167.74" z="0.00"/>
		<keypoint name="Front_Base_Right" visible="1" x="289.14" y="207.39" z="0.00"/>
		<keypoint name="Right_Junction" visible="1" x="332.50" y="184.10" z="0.00"/>
		<keypoint name="Handle_Front_Right" visible="1" x="297.30" y="170.96" z="0.00"/>
		<keypoint name="Handle_Right_Junction" visible="1" x="336.62" y="173.69" z="0.00"/>
	</keypoints>
	<polylinesegments>
		<segment name="foreground" x="293.10 289.63 289.63 297.05 498.35 498.84 498.35 480.05 478.56 444.93 371.24 360.85 " y="169.23 208.38 231.67 331.28 332.76 321.36 308.98 285.68 281.22 257.93 183.60 171.21 "/>
	</polylinesegments>
</annotation>
