<?xml version="1.0" encoding="utf-8"?>
<annotation>
	<image>2008_006872</image>
	<voc_id>2</voc_id>
	<category>car</category>
	<visible_bounds height="125.00" width="380.00" xmin="65.00" ymin="158.00"/>
	<keypoints>
		<keypoint name="L_F_WheelCenter" visible="1" x="130.64" y="258.04" z="0.00"/>
		<keypoint name="L_B_WheelCenter" visible="1" x="360.83" y="256.90" z="0.00"/>
		<keypoint name="L_HeadLight" visible="1" x="82.52" y="221.73" z="0.00"/>
		<keypoint name="L_TailLight" visible="1" x="433.28" y="209.97" z="0.00"/>
		<keypoint name="L_SideviewMirror" visible="1" x="195.46" y="196.29" z="0.00"/>
		<keypoint name="L_F_RoofTop" visible="1" x="225.84" y="167.17" z="0.00"/>
		<keypoint name="L_B_RoofTop" visible="1" x="326.58" y="163.70" z="0.00"/>
	</keypoints>
	<polylinesegments>
		<segment name="foreground" x="163.66 205.82 226.90 308.57 338.43 391.12 391.12 435.91 439.43 444.70 445.57 443.82 397.27 393.76 384.10 368.29 347.21 333.16 327.01 170.69 161.91 144.34 122.39 107.46 98.68 95.16 72.33 65.30 65.30 73.21 84.62 " y="190.68 166.12 158.22 155.59 162.61 181.91 186.29 188.92 197.69 217.87 230.15 247.69 259.09 277.51 281.90 287.16 286.29 279.27 266.11 266.99 281.90 283.65 285.41 285.41 268.74 266.11 263.48 254.71 229.27 213.48 204.71 "/>
	</polylinesegments>
</annotation>
