<?xml version="1.0" encoding="utf-8"?>
<annotation id="927">
   <image>2008_002954</image>
   <category>person</category>
   <subcategory>Female</subcategory>
   <visible_bounds height="384.00" width="182.00" xmin="56.00" ymin="77.00"/>
   <keypoints>
      <keypoint name="L_Ankle" visible="1" x="206.85" y="418.23" z="22.42" zorder="1"/>
      <keypoint name="L_Ear" visible="1" x="195.51" y="114.11" z="0.00" zorder="1"/>
      <keypoint name="L_Elbow" visible="1" x="216.77" y="206.69" z="26.31" zorder="0"/>
      <keypoint name="L_Eye" visible="1" x="189.30" y="102.88" z="0.00" zorder="1"/>
      <keypoint name="L_Hip" visible="1" x="186.61" y="244.12" z="13.69" zorder="1"/>
      <keypoint name="L_Knee" visible="1" x="200.65" y="335.28" z="17.45" zorder="0"/>
      <keypoint name="L_Shoulder" visible="1" x="209.95" y="145.74" z="21.24" zorder="0"/>
      <keypoint name="L_Toes" visible="1" x="221.54" y="440.14" z="34.09" zorder="0"/>
      <keypoint name="L_Wrist" visible="1" x="219.79" y="258.19" z="27.64" zorder="0"/>
      <keypoint name="Nose" visible="1" x="180.73" y="107.31" z="0.00" zorder="1"/>
      <keypoint name="R_Ankle" visible="1" x="116.61" y="425.24" z="26.51" zorder="1"/>
      <keypoint name="R_Ear" visible="1" x="157.38" y="107.61" z="0.00" zorder="1"/>
      <keypoint name="R_Elbow" visible="1" x="112.66" y="207.05" z="18.79" zorder="0"/>
      <keypoint name="R_Eye" visible="1" x="171.86" y="99.04" z="0.00" zorder="1"/>
      <keypoint name="R_Hip" visible="1" x="145.24" y="253.93" z="7.56" zorder="2"/>
      <keypoint name="R_Knee" visible="1" x="125.33" y="342.38" z="24.86" zorder="0"/>
      <keypoint name="R_Shoulder" visible="1" x="143.73" y="157.37" z="0.00" zorder="1"/>
      <keypoint name="R_Toes" visible="1" x="107.34" y="449.06" z="39.89" zorder="0"/>
      <keypoint name="R_Wrist" visible="1" x="81.64" y="221.83" z="57.29" zorder="0"/>
   </keypoints>
   <polylinesegments>
      <segment name="foreground" x="185 166 151 144 148 157 141 123 107 82 55 60 75 84 117 133 140 143 133 120 110 107 100 104 97 110 124 129 136 138 142 154 163 174 174 181 192 194 201 215 218 240 240 225 225 220 217 211 228 229 227 222 217 187 202 204 " y="78 78 88 100 121 133 147 159 194 214 214 235 235 230 221 196 177 204 228 273 328 361 402 427 454 461 453 431 413 383 342 308 286 286 309 348 376 414 437 442 450 449 439 424 397 357 314 287 279 247 202 157 143 132 124 97 "/>
   </polylinesegments>
</annotation>