<?xml version="1.0" encoding="utf-8"?>
<annotation id="1682">
   <image>2008_006818</image>
   <category>person</category>
   <subcategory>Male</subcategory>
   <visible_bounds height="48.00" width="18.00" xmin="74.00" ymin="134.00"/>
   <keypoints>
      <keypoint name="B_Head" visible="1" x="79.33" y="134.99" z="0.00" zorder="1"/>
      <keypoint name="L_Ankle" visible="1" x="80.82" y="177.32" z="-3.15" zorder="1"/>
      <keypoint name="L_Elbow" visible="1" x="75.69" y="148.32" z="-7.07" zorder="0"/>
      <keypoint name="L_Hip" visible="1" x="79.34" y="153.65" z="-3.69" zorder="1"/>
      <keypoint name="L_Knee" visible="1" x="80.06" y="166.09" z="-3.15" zorder="1"/>
      <keypoint name="L_Shoulder" visible="1" x="78.00" y="140.35" z="-7.47" zorder="2"/>
      <keypoint name="L_Wrist" visible="1" x="78.02" y="152.27" z="-12.32" zorder="2"/>
      <keypoint name="R_Ankle" visible="1" x="85.51" y="175.92" z="2.98" zorder="2"/>
      <keypoint name="R_Ear" visible="1" x="83.90" y="135.09" z="0.00" zorder="1"/>
      <keypoint name="R_Elbow" visible="1" x="86.00" y="147.42" z="4.40" zorder="0"/>
      <keypoint name="R_Hip" visible="1" x="83.71" y="153.32" z="0.11" zorder="0"/>
      <keypoint name="R_Knee" visible="1" x="87.20" y="164.80" z="3.52" zorder="0"/>
      <keypoint name="R_Shoulder" visible="1" x="85.23" y="140.41" z="0.00" zorder="1"/>
      <keypoint name="R_Wrist" visible="1" x="86.38" y="153.81" z="1.64" zorder="2"/>
   </keypoints>
   <polylinesegments>
      <segment name="foreground" x="80 79 79 78 75 75 78 78 83 83 87 89 87 91 88 87 87 85 84 80 79 79 79 79 79 79 " y="173 172 159 155 153 141 140 135 135 139 140 147 153 165 177 180 180 179 180 180 172 172 172 172 172 172 "/>
   </polylinesegments>
</annotation>