<?xml version="1.0" encoding="utf-8"?>
<annotation id="1983">
   <image>2008_008691</image>
   <category>person</category>
   <subcategory>Male</subcategory>
   <visible_bounds height="230.00" width="75.00" xmin="181.00" ymin="145.00"/>
   <keypoints>
      <keypoint name="L_Ankle" visible="1" x="228.83" y="366.15" z="9.75" zorder="1"/>
      <keypoint name="L_Ear" visible="1" x="228.09" y="163.22" z="0.00" zorder="1"/>
      <keypoint name="L_Elbow" visible="1" x="247.31" y="232.38" z="14.96" zorder="0"/>
      <keypoint name="L_Eye" visible="1" x="221.37" y="159.36" z="0.00" zorder="1"/>
      <keypoint name="L_Hip" visible="1" x="231.73" y="258.43" z="1.27" zorder="1"/>
      <keypoint name="L_Knee" visible="1" x="235.31" y="315.17" z="6.19" zorder="1"/>
      <keypoint name="L_Shoulder" visible="1" x="241.14" y="197.95" z="0.00" zorder="1"/>
      <keypoint name="L_Wrist" visible="1" x="243.77" y="255.55" z="36.60" zorder="0"/>
      <keypoint name="Nose" visible="1" x="217.17" y="165.07" z="0.00" zorder="1"/>
      <keypoint name="R_Ankle" visible="1" x="200.32" y="366.96" z="18.11" zorder="1"/>
      <keypoint name="R_Ear" visible="1" x="207.26" y="163.39" z="0.00" zorder="1"/>
      <keypoint name="R_Elbow" visible="1" x="184.87" y="233.16" z="15.29" zorder="0"/>
      <keypoint name="R_Eye" visible="1" x="213.65" y="159.36" z="0.00" zorder="1"/>
      <keypoint name="R_Hip" visible="1" x="205.24" y="260.17" z="1.18" zorder="1"/>
      <keypoint name="R_Knee" visible="1" x="204.45" y="317.00" z="6.25" zorder="1"/>
      <keypoint name="R_Shoulder" visible="1" x="193.62" y="199.44" z="0.00" zorder="1"/>
      <keypoint name="R_Wrist" visible="1" x="188.40" y="263.01" z="25.97" zorder="0"/>
   </keypoints>
   <polylinesegments>
      <segment name="foreground" x="219 204 205 188 182 182 182 187 194 191 194 195 195 199 206 207 209 215 217 224 224 224 225 226 222 231 239 239 248 246 255 255 233 228 230 224 " y="145 149 175 187 198 233 266 278 280 305 326 354 369 373 375 356 331 314 294 295 309 322 332 342 367 375 348 317 292 262 234 199 177 170 156 143 "/>
   </polylinesegments>
</annotation>