<?xml version="1.0" encoding="utf-8"?>
<annotation id="128">
   <image>2008_000461</image>
   <category>person</category>
   <subcategory>Male</subcategory>
   <visible_bounds height="109.00" width="57.00" xmin="94.00" ymin="79.00"/>
   <keypoints>
      <keypoint name="L_Ear" visible="1" x="143.54" y="105.12" z="0.00" zorder="1"/>
      <keypoint name="L_Hip" visible="0" x="145.43" y="178.10" z="1.88" zorder="1"/>
      <keypoint name="L_Shoulder" visible="0" x="156.32" y="135.03" z="2.29" zorder="0"/>
      <keypoint name="R_Elbow" visible="1" x="102.39" y="151.76" z="7.37" zorder="0"/>
      <keypoint name="R_Hip" visible="0" x="126.63" y="178.22" z="0.41" zorder="2"/>
      <keypoint name="R_Shoulder" visible="1" x="122.63" y="135.45" z="0.00" zorder="1"/>
      <keypoint name="R_Wrist" visible="1" x="113.10" y="171.62" z="9.36" zorder="0"/>
   </keypoints>
   <polylinesegments>
      <segment name="foreground" x="104 114 118 117 119 119 127 136 143 147 148 138 136 137 141 142 146 145 136 130 133 133 120 115 112 105 105 " y="137 132 127 120 104 98 91 86 87 90 96 100 109 120 126 138 141 148 154 160 168 173 173 170 159 149 140 "/>
   </polylinesegments>
</annotation>