<?xml version="1.0" encoding="utf-8"?>
<annotation id="419">
   <image>2008_001408</image>
   <category>person</category>
   <subcategory>Male</subcategory>
   <visible_bounds height="202.00" width="95.00" xmin="242.00" ymin="173.00"/>
   <keypoints>
      <keypoint name="L_Ear" visible="1" x="303.96" y="212.22" z="0.00" zorder="1"/>
      <keypoint name="L_Elbow" visible="1" x="319.51" y="291.48" z="59.81" zorder="0"/>
      <keypoint name="L_Eye" visible="1" x="295.73" y="204.69" z="0.00" zorder="1"/>
      <keypoint name="L_Hip" visible="1" x="299.44" y="327.70" z="28.14" zorder="1"/>
      <keypoint name="L_Shoulder" visible="1" x="309.46" y="246.96" z="38.79" zorder="0"/>
      <keypoint name="L_Wrist" visible="1" x="318.69" y="322.31" z="88.51" zorder="0"/>
      <keypoint name="Nose" visible="1" x="288.43" y="209.63" z="0.00" zorder="1"/>
      <keypoint name="R_Ear" visible="1" x="269.13" y="210.10" z="0.00" zorder="1"/>
      <keypoint name="R_Elbow" visible="1" x="252.71" y="296.14" z="3.30" zorder="0"/>
      <keypoint name="R_Eye" visible="1" x="281.13" y="204.69" z="0.00" zorder="1"/>
      <keypoint name="R_Hip" visible="1" x="269.10" y="325.96" z="10.65" zorder="2"/>
      <keypoint name="R_Shoulder" visible="1" x="260.06" y="246.55" z="0.00" zorder="1"/>
      <keypoint name="R_Wrist" visible="1" x="253.93" y="326.42" z="32.58" zorder="0"/>
   </keypoints>
   <polylinesegments>
      <segment name="foreground" x="288 304 311 308 311 303 301 322 337 327 326 328 319 317 255 257 250 247 249 248 242 249 259 276 272 267 264 267 269 " y="176 181 197 205 215 219 227 244 276 282 322 334 344 374 374 344 339 332 321 287 285 252 238 227 218 214 206 203 186 "/>
   </polylinesegments>
</annotation>