<?xml version="1.0" encoding="utf-8"?>
<annotation id="452">
   <image>2008_001501</image>
   <category>person</category>
   <subcategory>Male</subcategory>
   <visible_bounds height="133.00" width="63.00" xmin="20.00" ymin="135.00"/>
   <keypoints>
      <keypoint name="L_Ankle" visible="1" x="69.03" y="253.49" z="-30.04" zorder="2"/>
      <keypoint name="L_Ear" visible="1" x="70.01" y="147.78" z="0.00" zorder="1"/>
      <keypoint name="L_Elbow" visible="1" x="78.62" y="182.92" z="30.16" zorder="0"/>
      <keypoint name="L_Eye" visible="1" x="65.54" y="145.27" z="0.00" zorder="1"/>
      <keypoint name="L_Hip" visible="1" x="70.12" y="207.74" z="5.46" zorder="1"/>
      <keypoint name="L_Knee" visible="1" x="71.53" y="248.71" z="6.59" zorder="0"/>
      <keypoint name="L_Shoulder" visible="1" x="75.41" y="163.77" z="10.92" zorder="1"/>
      <keypoint name="L_Toes" visible="1" x="68.93" y="261.80" z="-20.28" zorder="0"/>
      <keypoint name="L_Wrist" visible="1" x="75.89" y="189.48" z="51.96" zorder="0"/>
      <keypoint name="Nose" visible="1" x="63.36" y="148.54" z="0.00" zorder="1"/>
      <keypoint name="R_Ankle" visible="1" x="50.11" y="254.37" z="-29.00" zorder="2"/>
      <keypoint name="R_Ear" visible="1" x="54.74" y="147.01" z="0.00" zorder="1"/>
      <keypoint name="R_Elbow" visible="1" x="30.93" y="172.85" z="23.07" zorder="0"/>
      <keypoint name="R_Eye" visible="1" x="59.43" y="145.27" z="0.00" zorder="1"/>
      <keypoint name="R_Hip" visible="1" x="51.04" y="207.69" z="5.46" zorder="1"/>
      <keypoint name="R_Knee" visible="1" x="51.53" y="248.65" z="7.55" zorder="0"/>
      <keypoint name="R_Shoulder" visible="1" x="43.04" y="164.56" z="0.00" zorder="1"/>
      <keypoint name="R_Toes" visible="1" x="48.03" y="263.01" z="-19.77" zorder="0"/>
      <keypoint name="R_Wrist" visible="1" x="25.46" y="182.92" z="42.92" zorder="0"/>
   </keypoints>
   <polylinesegments>
      <segment name="foreground" x="47 46 49 48 44 41 44 43 33 26 21 19 24 29 37 45 53 48 44 45 52 66 72 73 73 78 81 80 83 78 75 75 77 77 76 72 73 70 67 65 65 64 60 60 55 53 53 " y="266 260 254 242 238 210 197 171 177 188 189 186 176 171 166 160 156 150 149 142 136 136 142 151 158 162 169 179 188 195 197 205 221 236 246 254 263 267 267 258 251 246 226 243 252 257 265 "/>
   </polylinesegments>
</annotation>