<?xml version="1.0" encoding="utf-8"?>
<annotation id="1226">
   <image>2008_004036</image>
   <category>person</category>
   <subcategory>Male</subcategory>
   <visible_bounds height="68.00" width="41.00" xmin="265.00" ymin="115.00"/>
   <keypoints>
      <keypoint name="B_Head" visible="1" x="284.89" y="119.50" z="0.00" zorder="1"/>
      <keypoint name="L_Hip" visible="1" x="270.42" y="145.10" z="-25.86" zorder="2"/>
      <keypoint name="L_Knee" visible="1" x="276.73" y="158.53" z="-44.29" zorder="2"/>
      <keypoint name="L_Shoulder" visible="1" x="276.05" y="124.03" z="-14.42" zorder="2"/>
      <keypoint name="R_Ankle" visible="1" x="282.49" y="182.01" z="-37.24" zorder="1"/>
      <keypoint name="R_Elbow" visible="1" x="291.67" y="146.00" z="-8.01" zorder="2"/>
      <keypoint name="R_Hip" visible="1" x="275.91" y="151.09" z="-18.45" zorder="0"/>
      <keypoint name="R_Knee" visible="1" x="286.33" y="161.00" z="-37.24" zorder="2"/>
      <keypoint name="R_Shoulder" visible="1" x="284.64" y="134.38" z="0.00" zorder="0"/>
      <keypoint name="R_Toes" visible="1" x="287.96" y="182.91" z="-42.13" zorder="2"/>
      <keypoint name="R_Wrist" visible="1" x="301.14" y="149.71" z="-16.47" zorder="2"/>
   </keypoints>
   <polylinesegments>
      <segment name="foreground" x="265 268 268 274 279 282 284 287 291 299 296 295 295 296 300 305 305 296 288 286 283 288 291 289 289 297 298 280 280 272 266 265 " y="142 139 135 127 125 123 119 116 117 124 126 131 134 139 144 147 151 156 148 146 150 156 160 171 175 180 181 181 166 160 155 148 "/>
   </polylinesegments>
</annotation>