<?xml version="1.0" encoding="utf-8"?>
<annotation id="1968">
   <image>2008_007525</image>
   <category>person</category>
   <subcategory>Female</subcategory>
   <visible_bounds height="74.00" width="27.00" xmin="1.00" ymin="224.00"/>
   <keypoints>
      <keypoint name="B_Head" visible="1" x="11.87" y="231.95" z="0.00" zorder="1"/>
      <keypoint name="L_Ankle" visible="1" x="3.80" y="287.81" z="15.94" zorder="1"/>
      <keypoint name="L_Ear" visible="0" x="7.45" y="232.92" z="0.00" zorder="1"/>
      <keypoint name="L_Hip" visible="1" x="6.30" y="258.02" z="-0.09" zorder="1"/>
      <keypoint name="L_Knee" visible="1" x="6.03" y="274.23" z="7.49" zorder="1"/>
      <keypoint name="L_Shoulder" visible="1" x="5.50" y="239.09" z="-0.63" zorder="2"/>
      <keypoint name="L_Toes" visible="1" x="5.68" y="290.93" z="11.70" zorder="2"/>
      <keypoint name="R_Ankle" visible="1" x="9.45" y="287.98" z="-11.31" zorder="1"/>
      <keypoint name="R_Ear" visible="0" x="16.04" y="233.27" z="0.00" zorder="1"/>
      <keypoint name="R_Elbow" visible="1" x="22.54" y="251.38" z="0.50" zorder="0"/>
      <keypoint name="R_Hip" visible="1" x="14.56" y="258.86" z="0.46" zorder="0"/>
      <keypoint name="R_Knee" visible="1" x="13.33" y="272.29" z="-11.31" zorder="2"/>
      <keypoint name="R_Shoulder" visible="1" x="19.13" y="239.96" z="0.00" zorder="1"/>
      <keypoint name="R_Toes" visible="1" x="10.68" y="291.74" z="-15.26" zorder="2"/>
      <keypoint name="R_Wrist" visible="1" x="22.20" y="259.40" z="-5.48" zorder="2"/>
   </keypoints>
   <polylinesegments>
      <segment name="foreground" x="6 8 12 15 18 20 21 24 25 26 26 25 21 20 19 19 18 18 17 16 14 13 12 8 5 2 2 5 5 " y="229 226 225 225 228 232 236 243 250 255 260 264 264 258 253 263 268 275 281 287 288 292 294 292 294 296 238 233 228 "/>
   </polylinesegments>
</annotation>