<?xml version="1.0" encoding="utf-8"?>
<annotation id="1853">
   <image>2008_007962</image>
   <category>person</category>
   <subcategory>Female</subcategory>
   <visible_bounds height="301.00" width="115.00" xmin="74.00" ymin="42.00"/>
   <keypoints>
      <keypoint name="L_Ankle" visible="1" x="166.31" y="314.21" z="23.08" zorder="1"/>
      <keypoint name="L_Ear" visible="1" x="157.71" y="79.79" z="0.00" zorder="1"/>
      <keypoint name="L_Elbow" visible="1" x="181.70" y="98.01" z="65.46" zorder="0"/>
      <keypoint name="L_Eye" visible="1" x="144.90" y="76.24" z="0.00" zorder="1"/>
      <keypoint name="L_Hip" visible="1" x="159.46" y="183.00" z="20.00" zorder="1"/>
      <keypoint name="L_Knee" visible="1" x="168.55" y="251.73" z="20.00" zorder="1"/>
      <keypoint name="L_Shoulder" visible="1" x="169.49" y="105.84" z="21.58" zorder="0"/>
      <keypoint name="L_Toes" visible="1" x="164.60" y="335.71" z="25.11" zorder="0"/>
      <keypoint name="L_Wrist" visible="1" x="167.41" y="62.30" z="70.17" zorder="0"/>
      <keypoint name="Nose" visible="1" x="137.27" y="82.78" z="0.00" zorder="1"/>
      <keypoint name="R_Ankle" visible="1" x="144.93" y="316.82" z="17.68" zorder="1"/>
      <keypoint name="R_Elbow" visible="1" x="83.06" y="101.07" z="19.15" zorder="0"/>
      <keypoint name="R_Eye" visible="1" x="134.82" y="75.70" z="0.00" zorder="1"/>
      <keypoint name="R_Hip" visible="1" x="129.25" y="186.24" z="9.18" zorder="2"/>
      <keypoint name="R_Knee" visible="1" x="134.96" y="255.10" z="14.88" zorder="1"/>
      <keypoint name="R_Shoulder" visible="1" x="122.27" y="116.30" z="0.00" zorder="1"/>
      <keypoint name="R_Toes" visible="1" x="131.99" y="321.29" z="34.48" zorder="0"/>
      <keypoint name="R_Wrist" visible="1" x="82.51" y="62.38" z="21.42" zorder="0"/>
   </keypoints>
   <polylinesegments>
      <segment name="foreground" x="95 95 90 93 93 109 132 134 125 132 142 142 153 170 170 191 191 187 176 176 189 186 166 166 151 151 151 148 124 114 130 127 127 116 117 117 119 115 115 79 75 75 77 77 75 83 " y="46 65 73 92 92 102 101 97 74 58 48 48 42 46 46 86 86 111 138 163 216 336 343 343 341 341 341 327 326 319 310 282 282 181 162 162 137 122 122 108 99 99 67 67 46 42 "/>
   </polylinesegments>
</annotation>