<?xml version="1.0" encoding="utf-8"?>
<annotation id="2798">
   <image>2009_005181</image>
   <category>person</category>
   <subcategory>Female</subcategory>
   <visible_bounds height="374.00" width="351.00" xmin="149.00" ymin="1.00"/>
   <keypoints>
      <keypoint name="L_Eye" visible="1" x="456.60" y="107.86" z="0.00" zorder="1"/>
      <keypoint name="L_Hip" visible="1" x="283.71" y="296.70" z="-227.28" zorder="2"/>
      <keypoint name="L_Knee" visible="1" x="283.90" y="334.32" z="-502.84" zorder="2"/>
      <keypoint name="L_Shoulder" visible="1" x="448.73" y="248.69" z="24.78" zorder="0"/>
      <keypoint name="Nose" visible="1" x="382.63" y="132.52" z="0.00" zorder="1"/>
      <keypoint name="R_Eye" visible="1" x="382.63" y="66.47" z="0.00" zorder="1"/>
      <keypoint name="R_Hip" visible="1" x="218.14" y="168.75" z="-227.28" zorder="2"/>
      <keypoint name="R_Knee" visible="1" x="165.99" y="260.49" z="-484.60" zorder="2"/>
      <keypoint name="R_Shoulder" visible="0" x="359.84" y="57.32" z="0.00" zorder="0"/>
   </keypoints>
   <polylinesegments>
      <segment name="foreground" x="157 185 216 243 261 259 248 263 267 259 254 261 275 290 314 498 497 485 498 498 497 501 458 457 458 455 426 401 379 385 378 359 343 320 309 311 305 294 283 269 262 251 254 232 211 197 186 171 165 158 152 155 151 155 157 " y="156 136 124 123 116 108 102 89 73 58 37 19 7 4 1 2 139 152 146 198 217 375 377 348 325 304 302 309 311 319 329 326 323 314 303 315 325 340 343 338 325 312 303 292 280 273 268 274 271 263 253 234 217 194 168 "/>
   </polylinesegments>
</annotation>