<?xml version="1.0" encoding="utf-8"?>
<annotation>
	<image>2010_003671</image>
	<category>person</category>
	<visible_bounds height="76.00" width="42.00" xmin="237.00" ymin="233.00"/>
	<keypoints>
		<keypoint name="L_Elbow" visible="1" x="265.17" y="258.00" z="0.00"/>
		<keypoint name="L_Wrist" visible="1" x="274.12" y="266.26" z="0.00"/>
		<keypoint name="R_Shoulder" visible="1" x="260.26" y="246.18" z="0.00"/>
		<keypoint name="R_Elbow" visible="1" x="269.03" y="258.00" z="0.00"/>
		<keypoint name="R_Wrist" visible="1" x="277.46" y="266.26" z="0.00"/>
		<keypoint name="L_Knee" visible="1" x="266.93" y="272.05" z="0.00"/>
		<keypoint name="R_Hip" visible="1" x="249.61" y="263.97" z="0.00"/>
		<keypoint name="R_Knee" visible="1" x="264.88" y="280.31" z="0.00"/>
		<keypoint name="R_Ankle" visible="1" x="258.56" y="302.56" z="0.00"/>
		<keypoint name="R_Ear" visible="1" x="261.53" y="239.74" z="0.00"/>
		<keypoint name="HeadBack" visible="1" x="258.76" y="236.22" z="0.00"/>
	</keypoints>
	<polylinesegments>
		<segment name="foreground" x="238.14 238.84 240.77 243.93 249.02 253.76 256.74 258.85 263.94 267.98 268.16 266.22 263.94 264.64 273.07 278.69 278.69 275.53 272.02 264.47 261.48 259.03 257.97 265.70 268.16 267.28 267.45 266.75 262.89 260.96 263.06 257.62 252.88 250.78 252.00 253.76 254.81 254.81 250.95 247.79 242.35 " y="268.19 261.69 255.54 249.57 243.95 240.09 237.80 234.64 233.41 234.11 238.33 242.02 245.53 247.81 259.58 265.73 269.42 271.18 268.89 262.39 259.58 261.69 264.68 269.07 272.23 276.80 280.84 290.15 299.45 304.02 307.01 307.89 307.01 304.72 300.51 295.77 290.15 284.88 281.36 275.92 271.53 "/>
	</polylinesegments>
</annotation>
