<?xml version="1.0" encoding="utf-8"?>
<annotation>
	<image>2010_003625</image>
	<category>person</category>
	<visible_bounds height="205.00" width="206.00" xmin="66.00" ymin="166.00"/>
	<keypoints>
		<keypoint name="R_Shoulder" visible="1" x="144.60" y="276.25" z="0.00"/>
		<keypoint name="R_Elbow" visible="1" x="72.00" y="322.86" z="0.00"/>
		<keypoint name="L_Eye" visible="1" x="252.43" y="247.60" z="0.00"/>
		<keypoint name="R_Eye" visible="1" x="222.32" y="242.73" z="0.00"/>
		<keypoint name="Nose" visible="1" x="236.84" y="262.70" z="0.00"/>
	</keypoints>
	<polylinesegments>
		<segment name="foreground" x="250.41 259.46 266.60 269.45 252.79 238.51 213.75 189.00 164.24 149.00 129.01 114.73 80.92 65.69 68.55 105.68 137.58 140.91 156.62 235.18 235.65 237.56 " y="264.72 241.89 211.93 200.04 175.32 165.33 164.38 182.45 221.44 252.36 272.33 287.07 302.76 317.98 336.53 341.28 342.24 357.93 362.68 369.34 310.85 286.12 "/>
	</polylinesegments>
</annotation>
