<?xml version="1.0" encoding="utf-8"?>
<annotation>
	<image>2011_000646</image>
	<category>person</category>
	<visible_bounds height="290.00" width="197.00" xmin="162.00" ymin="85.00"/>
	<keypoints>
		<keypoint name="L_Shoulder" visible="1" x="308.43" y="207.88" z="0.00"/>
		<keypoint name="L_Elbow" visible="1" x="316.25" y="269.99" z="0.00"/>
		<keypoint name="L_Wrist" visible="1" x="243.77" y="278.93" z="0.00"/>
		<keypoint name="R_Shoulder" visible="1" x="171.07" y="198.50" z="0.00"/>
		<keypoint name="R_Elbow" visible="1" x="169.73" y="276.92" z="0.00"/>
		<keypoint name="R_Wrist" visible="1" x="175.77" y="352.65" z="0.00"/>
		<keypoint name="L_Hip" visible="1" x="326.10" y="326.51" z="0.00"/>
		<keypoint name="L_Eye" visible="1" x="277.55" y="158.29" z="0.00"/>
		<keypoint name="R_Eye" visible="1" x="252.95" y="152.48" z="0.00"/>
		<keypoint name="L_Ear" visible="1" x="301.94" y="166.11" z="0.00"/>
		<keypoint name="R_Ear" visible="1" x="177.78" y="146.22" z="0.00"/>
		<keypoint name="Nose" visible="1" x="263.91" y="168.34" z="0.00"/>
	</keypoints>
</annotation>
