<?xml version="1.0" encoding="utf-8"?>
<annotation>
	<image>2011_002106</image>
	<category>person</category>
	<visible_bounds height="199.00" width="65.00" xmin="155.00" ymin="98.00"/>
	<keypoints>
		<keypoint name="L_Shoulder" visible="1" x="163.43" y="139.40" z="0.00"/>
		<keypoint name="L_Elbow" visible="1" x="162.81" y="176.04" z="0.00"/>
		<keypoint name="L_Wrist" visible="1" x="161.43" y="200.41" z="0.00"/>
		<keypoint name="R_Shoulder" visible="1" x="206.21" y="133.42" z="0.00"/>
		<keypoint name="R_Elbow" visible="1" x="216.48" y="163.77" z="0.00"/>
		<keypoint name="R_Wrist" visible="1" x="216.02" y="184.93" z="0.00"/>
		<keypoint name="L_Hip" visible="1" x="168.79" y="182.02" z="0.00"/>
		<keypoint name="L_Knee" visible="1" x="176.92" y="239.81" z="0.00"/>
		<keypoint name="L_Ankle" visible="1" x="179.68" y="273.16" z="0.00"/>
		<keypoint name="R_Hip" visible="1" x="204.98" y="180.18" z="0.00"/>
		<keypoint name="R_Knee" visible="1" x="206.05" y="237.82" z="0.00"/>
		<keypoint name="R_Ankle" visible="1" x="198.31" y="273.85" z="0.00"/>
		<keypoint name="L_Ear" visible="1" x="168.64" y="117.48" z="0.00"/>
		<keypoint name="R_Ear" visible="1" x="191.64" y="115.18" z="0.00"/>
		<keypoint name="L_Foot" visible="1" x="181.06" y="281.89" z="0.00"/>
		<keypoint name="R_Foot" visible="1" x="200.07" y="289.18" z="0.00"/>
		<keypoint name="HeadBack" visible="1" x="178.30" y="110.12" z="0.00"/>
	</keypoints>
</annotation>
