<?xml version="1.0" encoding="utf-8"?>
<annotation>
	<image>2011_003778</image>
	<category>person</category>
	<visible_bounds height="252.00" width="100.00" xmin="93.00" ymin="123.00"/>
	<keypoints>
		<keypoint name="L_Shoulder" visible="1" x="179.87" y="196.39" z="0.00"/>
		<keypoint name="L_Elbow" visible="1" x="163.38" y="240.85" z="0.00"/>
		<keypoint name="L_Wrist" visible="1" x="119.71" y="204.54" z="0.00"/>
		<keypoint name="L_Hip" visible="1" x="167.07" y="274.04" z="0.00"/>
		<keypoint name="R_Hip" visible="1" x="111.75" y="276.57" z="0.00"/>
		<keypoint name="L_Eye" visible="1" x="166.09" y="148.24" z="0.00"/>
		<keypoint name="R_Eye" visible="1" x="149.79" y="150.38" z="0.00"/>
		<keypoint name="R_Ear" visible="1" x="139.22" y="163.39" z="0.00"/>
		<keypoint name="Nose" visible="1" x="161.44" y="158.34" z="0.00"/>
	</keypoints>
</annotation>
