<?xml version="1.0" encoding="utf-8"?>
<annotation>
	<image>2011_006739</image>
	<category>person</category>
	<visible_bounds height="122.00" width="52.00" xmin="70.00" ymin="91.00"/>
	<keypoints>
		<keypoint name="L_Shoulder" visible="1" x="111.65" y="112.90" z="0.00"/>
		<keypoint name="L_Elbow" visible="1" x="114.47" y="127.66" z="0.00"/>
		<keypoint name="L_Wrist" visible="1" x="116.07" y="141.76" z="0.00"/>
		<keypoint name="R_Shoulder" visible="1" x="84.27" y="112.81" z="0.00"/>
		<keypoint name="R_Elbow" visible="1" x="78.25" y="129.73" z="0.00"/>
		<keypoint name="R_Wrist" visible="1" x="73.83" y="141.38" z="0.00"/>
		<keypoint name="L_Hip" visible="1" x="109.48" y="142.13" z="0.00"/>
		<keypoint name="L_Knee" visible="1" x="114.47" y="168.45" z="0.00"/>
		<keypoint name="L_Ankle" visible="1" x="112.87" y="194.20" z="0.00"/>
		<keypoint name="R_Hip" visible="1" x="88.50" y="137.62" z="0.00"/>
		<keypoint name="R_Knee" visible="1" x="87.09" y="156.61" z="0.00"/>
		<keypoint name="R_Ankle" visible="1" x="88.97" y="177.38" z="0.00"/>
		<keypoint name="L_Eye" visible="1" x="100.64" y="103.97" z="0.00"/>
		<keypoint name="R_Eye" visible="1" x="94.81" y="104.63" z="0.00"/>
		<keypoint name="Nose" visible="1" x="97.53" y="106.89" z="0.00"/>
		<keypoint name="L_Foot" visible="1" x="114.84" y="206.42" z="0.00"/>
		<keypoint name="R_Foot" visible="1" x="86.53" y="185.65" z="0.00"/>
	</keypoints>
</annotation>
