<?xml version="1.0" encoding="utf-8"?>
<annotation>
	<image>2011_007179</image>
	<category>person</category>
	<visible_bounds height="204.00" width="204.00" xmin="3.00" ymin="167.00"/>
	<keypoints>
		<keypoint name="R_Shoulder" visible="1" x="84.88" y="241.20" z="0.00"/>
		<keypoint name="R_Elbow" visible="1" x="81.43" y="317.37" z="0.00"/>
		<keypoint name="R_Wrist" visible="1" x="155.45" y="337.78" z="0.00"/>
		<keypoint name="L_Knee" visible="1" x="126.69" y="287.37" z="0.00"/>
		<keypoint name="R_Knee" visible="1" x="121.03" y="356.16" z="0.00"/>
		<keypoint name="R_Eye" visible="1" x="128.42" y="213.41" z="0.00"/>
		<keypoint name="R_Ear" visible="1" x="106.57" y="212.47" z="0.00"/>
		<keypoint name="Nose" visible="1" x="130.93" y="220.48" z="0.00"/>
		<keypoint name="HeadBack" visible="1" x="87.56" y="179.02" z="0.00"/>
	</keypoints>
</annotation>
